vlc_helper/__init__.py
vlc_helper/repl.py
vlc_helper/vlc.py
vlc_helper/scripts/__init__.py
vlc_helper/scripts/myvlc.py
vlc_helper/scripts/repl.py
vlc_helper-0.1.9.dist-info/LICENSE.txt
vlc_helper-0.1.9.dist-info/METADATA
vlc_helper-0.1.9.dist-info/WHEEL
vlc_helper-0.1.9.dist-info/entry_points.txt
vlc_helper-0.1.9.dist-info/top_level.txt
vlc_helper-0.1.9.dist-info/RECORD
