Metadata-Version: 2.1
Name: vlc-helper
Version: 0.1.9
Summary: CLI helpers for VLC media player
Home-page: https://github.com/kenjyco/vlc-helper
Author: Ken
Author-email: kenjyco@gmail.com
License: MIT
Download-URL: https://github.com/kenjyco/vlc-helper/tarball/v0.1.9
Keywords: vlc,video,video player,cli,command-line,repl,dbus,screenshots,annotations,helper,kenjyco
Platform: UNKNOWN
Classifier: Development Status :: 3 - Alpha
Classifier: Environment :: Console
Classifier: Intended Audience :: Developers
Classifier: License :: OSI Approved :: MIT License
Classifier: Operating System :: POSIX :: Linux
Classifier: Programming Language :: Python :: 3.5
Classifier: Programming Language :: Python
Classifier: Topic :: Multimedia :: Video
Classifier: Topic :: Software Development :: Libraries
Classifier: Topic :: Utilities
Requires-Dist: bg-helper
Requires-Dist: chloop
Requires-Dist: click (>=6.0)
Requires-Dist: dbus-python
